setup.cfg
setup.py
docs/HISTORY
docs/LICENSE
docs/README
twisted/__init__.py
twisted.internet.processes.egg-info/PKG-INFO
twisted.internet.processes.egg-info/SOURCES.txt
twisted.internet.processes.egg-info/dependency_links.txt
twisted.internet.processes.egg-info/namespace_packages.txt
twisted.internet.processes.egg-info/not-zip-safe
twisted.internet.processes.egg-info/requires.txt
twisted.internet.processes.egg-info/top_level.txt
twisted/internet/__init__.py
twisted/internet/processes/__init__.py