Metadata-Version: 1.0
Name: twisted.internet.processes
Version: 1.0b1
Summary: An implementation of deferToProcess using the multiprocessing package.
Home-page: http://code.google.com/p/meercat
Author: Benjamin Liles (Texas A&M University)
Author-email: bliles@library.tamu.edu
License: Apache 2.0
Keywords: twisted multiprocessing deferToProcess
Platform: UNKNOWN
Classifier: Development Status :: 4 - Beta
Classifier: Framework :: Twisted
Classifier: Intended Audience :: Developers
Classifier: License :: OSI Approved :: Apache Software License
Classifier: Operating System :: OS Independent
Classifier: Programming Language :: Python
Classifier: Topic :: Software Development :: Libraries :: Python Modules
Classifier: Topic :: System :: Distributed Computing
